leidenalg-0.10.2.dist-info/WHEEL
leidenalg-0.10.2.dist-info/top_level.txt
leidenalg-0.10.2.dist-info/LICENSE
leidenalg-0.10.2.dist-info/RECORD
leidenalg-0.10.2.dist-info/METADATA
leidenalg/__init__.py
leidenalg/python_optimiser_interface.cpp
leidenalg/Optimiser.py
leidenalg/python_partition_interface.cpp
leidenalg/pynterface.cpp
leidenalg/functions.py
leidenalg/version.py
leidenalg/_c_leiden.cpython-37m-x86_64-linux-gnu.so
leidenalg/VertexPartition.py
leidenalg.libs/liblibleidenalg-3f9fe403.so.0.11.0
leidenalg.libs/libigraph-42015797.so.3.0.0
